{
    "version": "2.23.2",
    "homepage": "https://github.com/walles/riff",
    "description": "A diff filter highlighting which line parts have changed.",
    "license": "MIT",
    "suggest": {
        "moar": "moar"
    },
    "architecture": {
        "64bit": {
            "url": "https://github.com/walles/riff/releases/download/2.23.2/riff-2.23.2-x86_64-windows.exe#/riff.exe",
            "hash": "3b5853d88ed1e58936aa6b6419546f68fc415c151cfde6fc5c22d957438f1aa0",
            "bin": "riff.exe"
        }
    },
    "checkver": "github",
    "autoupdate": {
        "architecture": {
            "64bit": {
                "url": "https://github.com/walles/riff/releases/download/$version/riff-$version-x86_64-windows.exe#/riff.exe"
            }
        }
    }
}
